{
  "products": [
    {
      "id": 1,
      "productName": "Men's Casual Solid Lycra Shirt",
      "categoryId": 1,
      "description": "Latest Men’s Half Sleeves Shirt",
      "price": "₹1,120",
      "is_available": true,
      "productImg": "https://i.postimg.cc/vHj6n8jy/shirt1.jpg",
      "rating": 4.4,
      "review": 50,
      "vendor_name": "Malabar Textiles",
      "warranty": 1
    },
    {
      "id": 2,
      "productName": "Men's Smart Watch",
      "categoryId": 2,
      "description": "Latest Men’s Smart watch",
      "price": "₹1,500",
      "is_available": true,
      "productImg": "https://i.postimg.cc/FsCyBSQh/main-images-600x.webp",
      "rating": "4.2",
      "review": 100,
      "vendor_name": "Boat",
      "warranty": 1
    },
    {
      "id": 3,
      "productName": "Real Madrid Jersey",
      "categoryId": 1,
      "description": "Real Madrid 2022-2023 home Jersey ",
      "price": "₹3,500",
      "is_available": false,
      "productImg": "https://i.postimg.cc/dtG78TtW/RMCFMZ0073-01-500x480.webp",
      "rating": 4.9,
      "review": 250,
      "vendor_name": "Addidas",
      "warranty": 1
    },
    {
      "id": 4,
      "productName": "Allen Solly Share Allen Solly Blue Shirt",
      "categoryId": 1,
      "description": "Update your look with this Blue Solid Slim Fit shirt from Allen Solly by Allen Solly and enjoy the attention.",
      "price": "₹1,779",
      "is_available": true,
      "productImg": "https://i.postimg.cc/k4Q0H8nT/734684-8192066.webp",
      "rating": 4,
      "review": 100,
      "vendor_name": "Malabar Textiles",
      "warranty": 1
    },
    {
      "id": 5,
      "productName": "Men's Casual Watch",
      "categoryId": 2,
      "description": "Latest Men’s Fashion Watch ",
      "price": "₹7,500",
      "is_available": true,
      "productImg": "https://i.postimg.cc/9f581QKX/classic-watches-day-date-2022-roller-day-date-01.jpg",
      "rating": 5,
      "review": 500,
      "vendor_name": "Rolex",
      "warranty": 1
    },
    {
      "id": 6,
      "productName": "Women Fashion Dress",
      "categoryId": 1,
      "description": "Latest Women's Fashion Dress",
      "price": "₹7,400",
      "is_available": true,
      "productImg": "https://i.postimg.cc/gc5Bbvp3/d3.jpg",
      "rating": "4.0",
      "review": "200",
      "vendor_name": "Malabar Textiles",
      "warranty": "0"
    },
    {
      "id": 7,
      "productName": "Manchester United Jersey",
      "categoryId": 1,
      "description": "Manchester United Ronaldo Home Kit 2022-23",
      "price": "₹4,999",
      "is_available": true,
      "productImg": "https://i.postimg.cc/rmWfv00Y/Man-U-Home-Ronaldo-1.jpg",
      "rating": 4.7,
      "review": 320,
      "vendor_name": "Addidas",
      "warranty": 1
    },
    {
      "id": 8,
      "productName": "Men's Road Running Shoes",
      "categoryId": 1,
      "description": "Nike Air Zoom Pegasus 39 A.I.R. Hola Lou",
      "price": "₹11,895 ",
      "is_available": true,
      "productImg": "https://i.postimg.cc/RCJTpH57/2eecc06d-5915-4651-9cc6-eca519f5c350.webp",
      "rating": 4.7,
      "review": 500,
      "vendor_name": "Nike",
      "warranty": 2
    },
    {
      "id": 9,
      "productName": "boAt Rockerz 510",
      "categoryId": 2,
      "description": "boAt Rockerz 510 Now just stop worrying about Wires hanging from here and there. Pair with any Bluetooth device, connect and play. Dead Batteries can kill your vibe. boAt Rockerz 510 is designed to play Up to 20 hours. Don't just be loud, be loud and clear. We assure you have not heard such powerful bass and vocal clarity from a wireless comfortable headphone with Extra Comfort Ear cups. The boAt Super Bass Rockerz510 Wireless Headphones will make your listening experience personal and for real. So, just plug it in and Plug into Nirvana.",
      "price": "₹1,099",
      "is_available": true,
      "productImg": "https://i.postimg.cc/2SsxMK9x/5d5377dc-d3dd-48ba-8ec9-2a1630146d8d-600x.webp",
      "rating": 4.8,
      "review": 150,
      "vendor_name": "boAt",
      "warranty": 2
    },
    {
      "id": 10,
      "productName": "Monogram Motif Leather Large Tote",
      "categoryId": 1,
      "description": "Womens Fashion Black Monogram Motif Leather Large Tote",
      "price": "₹2,085",
      "is_available": true,
      "productImg": "https://i.postimg.cc/kGN4MB74/4-C955-FC9-12-F7-436-F-B190-C57-EC9-F0-D46-D.webp",
      "rating": 4.2,
      "review": 600,
      "vendor_name": "Monogram",
      "warranty": 1
    },
    {
      "id": 11,
      "productName": "Nike Brasilia",
      "categoryId": 1,
      "description": "The Nike Brasilia Printed Backpack is ready for the classroom with a main compartment to hold books and school supplies. A zip front pocket helps keep small items organised while side mesh pockets can each hold a water bottle.",
      "price": "₹1,995",
      "is_available": true,
      "productImg": "https://i.postimg.cc/CMR0YvFq/brasilia-backpack-sb3-KFZ.jpg",
      "rating": 4.5,
      "review": 37,
      "vendor_name": "Nike",
      "warranty": 1
    },
    {
      "id": 12,
      "productName": "Nike Sportswear Women's Woven Air Max Day Jacket",
      "categoryId": 1,
      "description": "With a look that's as clean as the shoe that inspired it, this woven jacket is ready to help you celebrate Air Max Day in style. Air Max-inspired details and crinkle-woven fabric insets at the shoulders accent the crisp fabric, while classic windbreaker design provides a familiar feel perfect for everyday layering.",
      "price": "₹7,295",
      "is_available": false,
      "productImg": "https://i.postimg.cc/nM85HGH8/4be9aa25-6449-42f7-bd27-4f618419ba8d.webp",
      "rating": 4.5,
      "review": 5,
      "vendor_name": "Nike",
      "warranty": 2
    },
    {
      "id": 13,
      "productName": "Nike Zoom Mercurial Vapor 15 Academy FG/MG By You",
      "categoryId": 1,
      "description": "Embrace the big stage in this custom Vapor 15. Express your creative side with a wide array of vibrant, eye-catching colors that are dialed for your distinct, brash style. With special design details like flamboyant color options to nods to the game’s biggest global event to personalized messages, there’s no limit to your creativity on or off the field. Now loaded with a Nike Air Zoom unit in the heel, you can put the pedal down in the waning minutes of a match — when it matters most. Fast is in the AIR.",
      "price": "₹10,990",
      "is_available": true,
      "productImg": "https://i.postimg.cc/50DY26Dd/ae02761a-07d8-4261-a24a-318348ae6d4b.webp",
      "rating": 4.9,
      "review": 25,
      "vendor_name": "Nike",
      "warranty": 2
    },
    {
      "id": 14,
      "productName": "ADILETTE COMFORT SLIDES",
      "categoryId": 1,
      "description": "Classics for a reason. These adidas slides are the perfect combination of versatility and comfort. They slip on and off easily for a conveniently snug fit. Go barefoot from the pool deck to the locker room, or pair them with track pants and socks for a casual and cosy fit around the house. A unique design shows some love for the Argentine Football Association.",
      "price": "₹4,599",
      "is_available": true,
      "productImg": "https://i.postimg.cc/tCs1Vt90/157978bdfceb49be85f2aec500d12310-9366.webp",
      "rating": 4.1,
      "review": 5,
      "vendor_name": "Addidas",
      "warranty": 2
    },
    {
      "id": 15,
      "productName": "GERMANY BEANIE",
      "categoryId": 1,
      "description": "A KNIT BEANIE FOR GERMANY SUPPORTERS, MADE IN PART WITH RECYCLED MATERIALS.",
      "price": "₹1,799",
      "is_available": true,
      "productImg": "https://i.postimg.cc/Hk9VGpmz/Germany-Beanie-Black-HP0769-01-standard.jpg",
      "rating": 4,
      "review": 2,
      "vendor_name": "Addidas",
      "warranty": 0
    },
    {
      "id": "17",
      "productName": "Amazfit GTS 2 Smart Watch",
      "categoryId": 2,
      "description": "(Renewed) Amazfit GTS 2 Smart Watch- Flamingo Pink, Metal (14 Days Battery Life 5 ATM)",
      "price": "₹4,489",
      "is_available": "yes",
      "productImg": "https://i.postimg.cc/D0ZgtCRf/51x-2s-HF8k-L-SX522.jpg",
      "rating": "4.5",
      "review": "140",
      "vendor_name": "Amazfit",
      "warranty": "1"
    },
    {
      "id": "18",
      "productName": "Sony Digital Vlog Camera",
      "categoryId": 2,
      "description": "Sony Digital Vlog Camera ZV 1 (Compact, Video Eye AF, Flip Screen, in-Built Microphone, Bluetooth Shooting Grip, 4K Vlogging Camera and Content Creation) - Black",
      "price": "₹54,990",
      "is_available": "yes",
      "productImg": "https://i.postimg.cc/8Pt8f5hx/61-EGyktwg-TL-SL1500.jpg",
      "rating": "4.3",
      "review": "234",
      "vendor_name": "Sony",
      "warranty": "1"
    },
    {
      "id": "19",
      "productName": "Silver Chain",
      "categoryId": "3",
      "description": " Silver Jewellery, often worn by men and women alike, is recorded as a robust antimicrobial agent. it's thought that silver symbolises purity and clarity. It's a relatively tough metal and so is indicative of strength – in the wearer, it can send messages of focus and strength of purpose.",
      "price": "₹1,648",
      "is_available": "yes",
      "productImg": "https://i.postimg.cc/t4tV8ZZy/49331326-01-oshnm0o6i4czs0vt.webp",
      "rating": "4.4",
      "review": "15",
      "vendor_name": "Bhima Jewellers",
      "warranty": "2"
    },
    {
      "id": "20",
      "productName": "Silver Blue Link Chain",
      "categoryId": "3",
      "description": "Silver Mystic Blue Leaf Pendant with Link Chain",
      "price": "₹1,999",
      "is_available": "yes",
      "productImg": "https://i.postimg.cc/j5gfZLgc/PD0194-3-2-1024x1024.webp",
      "rating": "4.9",
      "review": "25",
      "vendor_name": "GIVA",
      "warranty": "2"
    },
    {
      "id": "21",
      "productName": "JBL Bluetooth Speaker",
      "categoryId": "2",
      "description": "JBL Go Essential with Rich Bass, 5 Hrs Playtime, IPX7 Waterproof, Ultra Portable 3.1 W Bluetooth Speaker  (Black, Mono Channel)",
      "price": "₹1,299",
      "is_available": "yes",
      "productImg": "https://i.postimg.cc/3NZbNjn1/original-imagdhhg2f7zjbt7.webp",
      "rating": "4.2",
      "review": "175",
      "vendor_name": "JBL",
      "warranty": "1"
    },
    {
      "id": "22",
      "productName": "Suitcase",
      "categoryId": "1",
      "description": "Large Check-in Suitcase (77 cm) - Agile Plus 4W - Grey",
      "price": "₹3,249",
      "is_available": "no",
      "productImg": "https://i.postimg.cc/1t78QbZr/original-imagg7nudfa7xkaf.webp",
      "rating": "4.6",
      "review": "7",
      "vendor_name": "Agile",
      "warranty": "0"
    },
    {
      "id": "23",
      "productName": " Kurta (Maroon)",
      "categoryId": "1",
      "description": "Women Embroidered Viscose Rayon A-line Kurta  (Maroon)",
      "price": "₹399",
      "is_available": "yes",
      "productImg": "https://i.postimg.cc/8khCwF7b/s-kr-06-wine-kriska-original-imafxqutadagxnqh-bb.webp",
      "rating": "4.1",
      "review": "3025",
      "vendor_name": "Malabar Textiles",
      "warranty": "0"
    },
    {
      "id": "24",
      "productName": "Grey Jeans",
      "categoryId": "1",
      "description": "U.S. POLO ASSN.  Slim Men Grey Jeans",
      "price": "₹1,049",
      "is_available": "yes",
      "productImg": "https://i.postimg.cc/KvMD0DnH/32-udjeno0574-u-s-polo-association-original-imaggr7rykfh8vbp.webp",
      "rating": "3.9",
      "review": "3",
      "vendor_name": "U.S. POLO ",
      "warranty": "0"
    },
    {
      "id": "25",
      "productName": "Black Red Dragon Finger Ring",
      "categoryId": "3",
      "description": "Dragon Black Red Base Stainless Steel Finger Ring - Thumb Ring Valentine gift Intelligent Smart Ring Fashion Jewellery Collection propose Lovers Fancy Party wear Stylish latest design Heart king Couples Love Golden Black Blue Mens Style Thumb Smart Band Gold plated Name Letter Hand Finger Rings Combo set pack for men / Boys / boyfriend / husband /gents /girls / Ladies / women / Wife / girlfriend /Couple Latest Simple Single Daily use Gift High Trendy style , Tungsten, Metal, Brass, Enamel, Alloy Titanium, Gold, Black Silver, Rhodium Plated Ring",
      "price": "₹191",
      "is_available": "yes",
      "productImg": "https://i.postimg.cc/q7xTyKbt/21-hc-332-black-red-dragon-finger-ring-size-21-ring-heer-original-imag38qzkf2wbj3j.webp",
      "rating": "4.1",
      "review": "222",
      "vendor_name": " Heer Collection",
      "warranty": "0"
    },
    {
      "id": "26",
      "productName": "Stud Earring",
      "categoryId": "3",
      "description": "Femme Jam 925 Sterling Silver, Diamond White Color, Round Unisex Stud Earring. White Gold Swarovski Stud Earring",
      "price": "₹799",
      "is_available": "yes",
      "productImg": "https://i.postimg.cc/nzWwDcJj/na-soli-swa-round-ear-stud-6mm-fhs-highspark-original-imag7rtszzg3srz7.webp",
      "rating": "4.4",
      "review": "58",
      "vendor_name": "Femme Jam",
      "warranty": "0"
    },
    {
      "id": "27",
      "productName": "Nike Liverpool F.C. Strike Football",
      "categoryId": "4",
      "description": "The Liverpool F.C. Strike Football is ready to fly into the back of the net. A textured casing and stabilising grooves help you put the ball right where you want it.",
      "price": "₹1,995",
      "is_available": "yes",
      "productImg": "https://i.postimg.cc/gcQ2Yvfd/edb889a6-96de-4599-bd13-0812946d33ac.webp",
      "rating": "4.5",
      "review": "22",
      "vendor_name": "Nike",
      "warranty": "1"
    }
  ]
}